nocaps_cli/__init__.py
nocaps_cli/authorization_device_code.py
nocaps_cli/authorization_pkce.py
nocaps_cli/nocaps.py
nocaps-0.7.1.dist-info/METADATA
nocaps-0.7.1.dist-info/WHEEL
nocaps-0.7.1.dist-info/entry_points.txt
nocaps-0.7.1.dist-info/top_level.txt
nocaps-0.7.1.dist-info/RECORD
