Metadata-Version: 2.4
Name: nocaps
Version: 0.7.1
Summary: A witty Python code roaster and fixer CLI tool.
Requires-Dist: rich
Requires-Dist: requests
Requires-Dist: keyring
Dynamic: requires-dist
Dynamic: summary
